[
  {
    "id": 1,
    "title": "Saiyara",
    "artist": "Artist A",
    "cover": "assets/covers2/song1.jpeg",
    "src": "https://github.com/Sumitchauhan-co/Js-Project-3/releases/download/v1.0.0/song1.mp3"
  },
  {
    "id": 2,
    "title": "Pahle Bhi Mein",
    "artist": "Artist B",
    "cover": "assets/covers2/song2.jpeg",
    "src": "https://github.com/Sumitchauhan-co/Js-Project-3/releases/download/v1.0.0/song2.mp3"
  },
  {
    "id": 3,
    "title": "Finding Her",
    "artist": "Artist C",
    "cover": "assets/covers2/song3.jpeg",
    "src": "https://github.com/Sumitchauhan-co/Js-Project-3/releases/download/v1.0.0/song3.mp3"
  },
  {
    "id": 4,
    "title": "Hua Hain Aaj Pahle Baar",
    "artist": "Artist D",
    "cover": "assets/covers2/song4.jpeg",
    "src": "https://github.com/Sumitchauhan-co/Js-Project-3/releases/download/v1.0.0/song4.mp3"
  },
  {
    "id": 5,
    "title": "Raatein Guzari",
    "artist": "Artist E",
    "cover": "assets/covers2/song5.jpeg",
    "src": "https://github.com/Sumitchauhan-co/Js-Project-3/releases/download/v1.0.0/song5.mp3"
  },
  {
    "id": 6,
    "title": "Thodi Jagah",
    "artist": "Artist F",
    "cover": "assets/covers2/song6.jpeg",
    "src": "https://github.com/Sumitchauhan-co/Js-Project-3/releases/download/v1.0.0/song6.mp3"
  },
  {
    "id": 7,
    "title": "Tu Jo Hai",
    "artist": "Artist G",
    "cover": "assets/covers2/song7.jpeg",
    "src": "https://github.com/Sumitchauhan-co/Js-Project-3/releases/download/v1.0.0/song7.mp3"
  }
]